{
  "Changes": [
    {
      "LogName": "Companion dialogues for Lenny", //Change Name
      "Action": "EditData",
      "Target": "Characters/Dialogue/Lenny", //Change Name
      "Entries": {
        "companionAccepted": "{{i18n:Lenny.Dialogue.companionAccepted}}",
        "companionRejected": "{{i18n:Lenny.Dialogue.companionRejected}}",
        "companionRejectedNight": "{{i18n:Lenny.Dialogue.companionRejectedNight}}",
        "companionDismiss": "{{i18n:Lenny.Dialogue.companionDismiss}}",
        "companionDismissAuto": "{{i18n:Lenny.Dialogue.companionDismissAuto}}",
        "companionRecruited": "{{i18n:Lenny.Dialogue.companionRecruited}}",

        "farmerRunAway": "{{i18n:Lenny.Dialogue.farmerRunAway}}",

      //Locations (Farm)
        //Friends
        //Weather
        "companion_Farm_Rainy": "{{i18n:Lenny.Dialogue.companion_Farm_Rainy}}",
        "companion_Farm_Snowy": "{{i18n:Lenny.Dialogue.companion_Farm_Snowy}}",

      //Locations (Others)

        "companion_Town": "{{i18n:Lenny.Dialogue.companion_Town}}",
        "companion_Custom_Ridgeside_RidgesideVillage": "{{i18n:Lenny.Dialogue.companion_Custom_Ridgeside_RidgesideVillage~{{Random:0,1}}}}",

      //Suggestion
        "companionSuggest": "{{i18n:Lenny.Dialogue.companionSuggest}}",

        "companionSuggest_Yes": "{{i18n:Lenny.Dialogue.companionSuggest_Yes}}",
        "companionSuggest_No": "{{i18n:Lenny.Dialogue.companionSuggest_No}}",

      }
    },

    {
      "Action": "EditData",
      "Target": "Characters/Dialogue/Lenny",
      "When": { "Season": "spring" },
      "Entries": {
        "companion_Farm": "{{i18n:Lenny.Dialogue.companion_Farm~{{Random:{{Random: 0, 1}}, spring}}}}",
        "companion_Farm_Dating": "{{i18n:Lenny.Dialogue.companion_Farm_Dating~{{Random:{{Random: 0, 1}}, spring}}}}",
        "companion_Farm_Spouse": "{{i18n:Lenny.Dialogue.companion_Farm_Spouse~{{Random:{{Random: 0, 1}}, spring}}}}",
      }
    },

    {
      "Action": "EditData",
      "Target": "Characters/Dialogue/Lenny",
      "When": { "Season": "summer" },
      "Entries": {
        "companion_Farm": "{{i18n:Lenny.Dialogue.companion_Farm~{{Random:{{Random: 0, 1}}, summer}}}}",
      }
    },

    {
      "Action": "EditData",
      "Target": "Characters/Dialogue/Lenny",
      "When": { "Season": "fall" },
      "Entries": {
        "companion_Farm": "{{i18n:Lenny.Dialogue.companion_Farm~{{Random:{{Random: 0, 1}}, fall}}}}",
      }
    },

    {
      "Action": "EditData",
      "Target": "Characters/Dialogue/Lenny",
      "When": { "Season": "winter" },
      "Entries": {
        "companion_Farm": "{{i18n:Lenny.Dialogue.companion_Farm~{{Random:{{Random: 0, 1}}, winter}}}}",
      }
    },
  ]
}
