{
	"Summit House Upgrade": {
		"translationKey": "SummitHouseUpgrade",
		"materials": "388 500 709 500 390 250",
		"price": 150000,
		"buildDuration": 2,
		"imgWidth": 128,
		"imgHeight": 128,
	},
	"Climate Control": {
		"translationKey": "ClimateControl",
		"materials": "495 100 496 100 497 100",
		"price": 2000000,
		"buildDuration": 2,
		"imgWidth": 128,
		"imgHeight": 160,
	},
	"Sprinkler System": {
		"translationKey": "SprinklerSystem",
		"materials": "645 25 371 50",
		"price": 1000000,
		"buildDuration": 2,
		"imgWidth": 128,
		"imgHeight": 160,
	},
	"Ore Area": {
		"translationKey": "OreArea",
		"materials": "709 150 286 50 337 10",
		"price": 250000,
		"buildDuration": 2,
		"imgWidth": 128,
		"imgHeight": 160,
	},
}
