{
"Changes": [

	{
		"LogName": "Jeric Base Schedule",
		"Action": "EditData",
		"Target": "Characters/Schedules/Jeric",
		"Entries": {

			"spring": "610 Custom_Ridgeside_RidgesideVillage 19 27 3 square_1_5_3/a900 Custom_Ridgeside_JericHouse 2 13 2/1800 Custom_Ridgeside_RidgesideVillage 38 28 0 square_3_1_0/2000 Custom_Ridgeside_JericHouse 18 5 0 jeric_sleep",
			"summer": "610 Custom_Ridgeside_RidgesideVillage 19 27 3 square_1_5_3/a900 Custom_Ridgeside_JericHouse 2 13 2/1800 Custom_Ridgeside_RidgesideVillage 38 28 0 square_3_1_0/2000 Custom_Ridgeside_JericHouse 18 5 0 jeric_sleep",
			"fall": "610 Custom_Ridgeside_RidgesideVillage 19 27 3 square_1_5_3/a900 Custom_Ridgeside_JericHouse 2 13 2/1800 Custom_Ridgeside_RidgesideVillage 38 28 0 square_3_1_0/2000 Custom_Ridgeside_JericHouse 18 5 0 jeric_sleep",
			"winter": "610 Custom_Ridgeside_RidgesideVillage 11 26 3/a900 Custom_Ridgeside_JericHouse 2 13 2/1800 Custom_Ridgeside_RidgesideVillage 39 20 3/2000 Custom_Ridgeside_JericHouse 18 5 0 jeric_sleep",
			"rain": "610 Custom_Ridgeside_RidgesideVillage 39 20 3/a900 Custom_Ridgeside_JericHouse 2 13 2/1800 Custom_Ridgeside_JericHouse 12 5 0/2000 Custom_Ridgeside_JericHouse 18 5 0 jeric_sleep",
			"GreenRain": "0 Custom_Ridgeside_JericHouse 3 5 2 square_4_2",
			"Sat": "800 Town 27 23 2/1500 Beach 41 8 2/1900 Custom_Ridgeside_JericHouse 18 5 0 jeric_sleep",
			"Tue": "GOTO Sat",
			"Thu": "610 Custom_Ridgeside_RidgesideVillage 19 27 3 square_1_5_3/800 Custom_Ridgeside_3Bros 9 9 0/1300 Custom_Ridgeside_RidgesideVillage 38 28 0 square_3_1_0/2000 Custom_Ridgeside_JericHouse 18 5 0 jeric_sleep",
			"spring_12": "610 Custom_Ridgeside_RidgesideVillage 19 27 3 square_1_5_3/a900 Custom_Ridgeside_JericHouse 2 13 2/a1400 Custom_Ridgeside_PaulaClinic 18 5 3 \"Strings\\schedules\\Jeric:checkup\"/1530 Custom_Ridgeside_JericHouse 2 13 2/1900 Custom_Ridgeside_RidgesideVillage 39 20 3/2000 Custom_Ridgeside_JericHouse 18 5 0 jeric_sleep",
			"winter_17": "610 Custom_Ridgeside_RidgesideVillage 11 26 3/900 Custom_Ridgeside_JericHouse 2 13 2/1200 Beach 11 30 3/2600 Custom_Ridgeside_JericHouse 18 5 0 jeric_sleep",

			//Marriage Schedule
			"marriage_Mon": "800 Custom_Ridgeside_JericHouse 2 13 2/1800 Custom_Ridgeside_RidgesideVillage 38 28 0 square_3_1_0/2200 bed",
			"marriage_Tue": "GOTO marriage_Mon",
			"marriage_Thu": "GOTO marriage_Mon",
			"marriage_Sat": "1000 Town 27 23 2/1300 Beach 41 8 2/1800 bed",
			"marriage_spring_12": "a1400 Custom_Ridgeside_PaulaClinic 18 5 3 \"Strings\\schedules\\Jeric:checkup_married\"/1530 Custom_Ridgeside_RidgesideVillage 38 28 0 square_3_1_0/1900 bed",
			"marriage_winter_17": "1000 Town 27 23 2/1600 Beach 11 30 3/2200 bed",

					},
	},

	//Greenhouse schedule
	{
		"Action": "EditData",
		"Target": "Characters/Schedules/Jeric",
		"Entries": {
			"Mon": "610 Custom_Ridgeside_RSVGreenhouse1 39 22 0 square_5_1_0/a1000 Custom_Ridgeside_JericHouse 2 13 2/1800 Custom_Ridgeside_RidgesideVillage 38 28 0 square_3_1_0/2000 Custom_Ridgeside_JericHouse 18 5 0 jeric_sleep",
					},
		"When": {
			"HasFlag: hostPlayer |contains=GH1letter": true,
		}
	},

]
}
