{
	"Changes":
	[
		/*********
		** Custom NPC Exclusions
		*********/
		{
			"Action": "EditData",
			"Target": "Data/CustomNPCExclusions",
			"Entries":
			{
				"Kiwi": "TownEvent TownQuest OtherEvent",
				"Undreya": "ALL",
				"Helen": "ALL",
				"Belinda": "ALL",
				"Bliss": "ALL",
				"Sari": "ALL",
				"Pipo": "ALL",
				"Acorn": "ALL",
				"Naomi": "TownEvent TownQuest",
				"Malaya": "TownEvent TownQuest",
				"Kimpoi": "TownEvent TownQuest",
				"Raeriyala": "ALL",
				"Zayne": "ALL",
				"Bryle": "ALL",
				"Daia": "TownEvent TownQuest OtherEvent",
				"Jio": "TownEvent TownQuest IslandEvent OtherEvent",
				"TreehouseGirl": "ALL",
				"RelicSpirit": "ALL",
				"Anton": "ItemDelivery",
				"Ariah": "ItemDelivery",
				"Blair": "ItemDelivery",
				"Carmen": "ItemDelivery",
				"Faye": "ItemDelivery",
				"Irene": "ItemDelivery",
				"Kiarra": "ItemDelivery",
				"Lorenzo": "ItemDelivery",
				"Louie": "ItemDelivery",
				"Maive": "ItemDelivery",
				"Paula": "ItemDelivery",
				"Sean": "ItemDelivery",
				"Shanice": "ItemDelivery",
				"Sonny": "ItemDelivery",
				"Torts": "ItemDelivery WinterStar",
				"Althea": "ALL",
				"Lorraine": "ALL",
				"Nadaline": "ALL",
				"Zachary": "ALL",
			}
		},
	],
}
