{
  "Name": "RingSpirit",
  "Type": "Flying",
  "TileSheetPath": "Characters\\RSVSpirits\\RingSpirit0",
  "FrameSizeWidth": 16,
  "FrameSizeHeight": 32,
  "TravelSpeed": 1,

  "IdleBehavior": "Hover",
  "IdleArguments": [ -1 ],
  "MaxDistanceBeforeTeleport": -1,
  "MaxIdleDistance": 2,

  "EnableBreathing": false,
  "EnableFarmerCollision": false,
  "EnableShadow": true,
  "Shadow": {
    "OffsetX": 0,
    "OffsetY": 8,
    "Scale": 1,
    "Alpha": 255
  },

  "DownAnimation": {
    "StartingFrame": 0,
    "NumberOfFrames": 4,
    "Duration": 500,

    "IdleAnimation": {
      "StartingFrame": 0,
      "NumberOfFrames": 4,
      "Duration": 800
    }
  },

  "RightAnimation": {
    "StartingFrame": 12,
    "NumberOfFrames": 4,
    "Duration": 500,

    "IdleAnimation": {
      "StartingFrame": 12,
      "NumberOfFrames": 4,
      "Duration": 800
    }
  },

  "UpAnimation": {
    "StartingFrame": 8,
    "NumberOfFrames": 4,
    "Duration": 500,

    "IdleAnimation": {
      "StartingFrame": 8,
      "NumberOfFrames": 4,
      "Duration": 800
    }
  },

  "LeftAnimation": {
    "StartingFrame": 4,
    "NumberOfFrames": 4,
    "Duration": 500,

    "IdleAnimation": {
      "StartingFrame": 4,
      "NumberOfFrames": 4,
      "Duration": 800
    }
  },
}
